cleanit/__init__.py
cleanit/__main__.py
cleanit/cleaner.py
cleanitall-0.1.1.dist-info/licenses/LICENSE
cleanitall-0.1.1.dist-info/METADATA
cleanitall-0.1.1.dist-info/WHEEL
cleanitall-0.1.1.dist-info/entry_points.txt
cleanitall-0.1.1.dist-info/top_level.txt
cleanitall-0.1.1.dist-info/RECORD
