Metadata-Version: 2.4
Name: cleanitall
Version: 0.1.1
Summary: A simple Python junk cleaner for developers
Home-page: https://github.com/inevitablegs/cleanitall
Author: Ganesh Sonawane
License: MIT
Classifier: Development Status :: 3 - Alpha
Classifier: Intended Audience :: Developers
Classifier: License :: OSI Approved :: MIT License
Classifier: Programming Language :: Python :: 3
Classifier: Programming Language :: Python :: 3.7
Classifier: Operating System :: OS Independent
Requires-Python: >=3.7
License-File: LICENSE
Dynamic: license-file
